MANIFEST.in
README.md
setup.py
notiadb/__init__.py
notiadb/notiadb.py
notiadb.egg-info/PKG-INFO
notiadb.egg-info/SOURCES.txt
notiadb.egg-info/dependency_links.txt
notiadb.egg-info/top_level.txt