Metadata-Version: 1.2
Name: notiadb
Version: 0.6
Summary: A basic database system for Python.
Home-page: https://github.com/kyshi/NotiaDB
Author: Kyshi
Author-email: kyshi58@outlook.com
License: UNKNOWN
Keywords: database
Platform: UNKNOWN
Classifier: Development Status :: 3 - Alpha
Classifier: Programming Language :: Python :: 3
Classifier: License :: OSI Approved :: MIT License
Classifier: Operating System :: OS Independent
Requires-Python: >=3.6
